netbox_python/__init__.py
netbox_python/baseapi.py
netbox_python/exceptions.py
netbox_python/netbox.py
netbox_python/rest.py
netbox_python/test_full.py
netbox_python/testit.py
netbox_python/testit2.py
netbox_python/testit3.py
netbox_python/api/__init__.py
netbox_python/api/asn_range.py
netbox_python/api/circuits.py
netbox_python/api/core.py
netbox_python/api/dcim.py
netbox_python/api/extras.py
netbox_python/api/ip_range.py
netbox_python/api/ipam.py
netbox_python/api/plugins.py
netbox_python/api/prefix.py
netbox_python/api/tenancy.py
netbox_python/api/users.py
netbox_python/api/virtualization.py
netbox_python/api/vlan_group.py
netbox_python/api/vpn.py
netbox_python/api/wireless.py
netbox_python-0.1.8.dist-info/LICENSE
netbox_python-0.1.8.dist-info/METADATA
netbox_python-0.1.8.dist-info/WHEEL
netbox_python-0.1.8.dist-info/top_level.txt
netbox_python-0.1.8.dist-info/RECORD
