Metadata-Version: 2.1
Name: netbox_python
Version: 0.1.8
Summary: NetBox Python API Client.
Author-email: Arthur Hanson <ahanson@netboxlabs.com>
Project-URL: Documentation, https://github.com/netbox-community/netbox_python/blob/main/README.md
Project-URL: Source, https://github.com/netbox-community/netbox_python
Project-URL: Tracker, https://github.com/netbox-community/netbox_python/issues
Classifier: Development Status :: 3 - Alpha
Classifier: Intended Audience :: Developers
Classifier: Natural Language :: English
Classifier: Programming Language :: Python :: 3 :: Only
Classifier: Programming Language :: Python :: 3.8
Classifier: Programming Language :: Python :: 3.9
Classifier: Programming Language :: Python :: 3.10
Classifier: Programming Language :: Python :: 3.11
Requires-Python: >=3.8.1
License-File: LICENSE
Requires-Dist: requests <3.0,>=2.20.0
Provides-Extra: test
Requires-Dist: bandit[toml] ==1.7.5 ; extra == 'test'
Requires-Dist: black ==23.3.0 ; extra == 'test'
Requires-Dist: check-manifest ==0.49 ; extra == 'test'
Requires-Dist: flake8-bugbear ==23.5.9 ; extra == 'test'
Requires-Dist: flake8 ; extra == 'test'
Requires-Dist: flake8-pyproject ; extra == 'test'
Requires-Dist: pre-commit ==3.3.1 ; extra == 'test'
Requires-Dist: pylint ==2.17.4 ; extra == 'test'
Requires-Dist: pytest-mock <3.10.1 ; extra == 'test'
Requires-Dist: pytest-runner ; extra == 'test'
Requires-Dist: pytest ==7.3.1 ; extra == 'test'
Requires-Dist: pytest-github-actions-annotate-failures ; extra == 'test'
Requires-Dist: shellcheck-py ==0.9.0.2 ; extra == 'test'
